setup.cfg
setup.py
ceh_core_infa/__init__.py
ceh_core_infa/config.py
ceh_core_infa.egg-info/PKG-INFO
ceh_core_infa.egg-info/SOURCES.txt
ceh_core_infa.egg-info/dependency_links.txt
ceh_core_infa.egg-info/not-zip-safe
ceh_core_infa.egg-info/requires.txt
ceh_core_infa.egg-info/top_level.txt
ceh_core_infa/libs/__init__.py
ceh_core_infa/libs/af_lib/__init__.py
ceh_core_infa/libs/af_lib/dynamic_dag.py
ceh_core_infa/libs/af_lib/utils.py
ceh_core_infa/libs/af_lib/dag_factory/__init__.py
ceh_core_infa/libs/af_lib/dag_factory/base_dag_builder.py
ceh_core_infa/libs/af_lib/dag_factory/control_dag_builder.py
ceh_core_infa/libs/af_lib/dag_factory/slave_dag_builder.py
ceh_core_infa/libs/af_lib/dag_factory/utils.py
ceh_core_infa/libs/af_lib/operators/__init__.py
ceh_core_infa/libs/af_lib/operators/ceh_base_operator.py
ceh_core_infa/libs/af_lib/operators/check_block_resource_operator.py
ceh_core_infa/libs/af_lib/operators/check_resource_locking_operator.py
ceh_core_infa/libs/af_lib/operators/check_state_services_operator.py
ceh_core_infa/libs/af_lib/operators/check_version_resource_operator.py
ceh_core_infa/libs/af_lib/operators/commit_transaction_operator.py
ceh_core_infa/libs/af_lib/operators/create_tx_operator.py
ceh_core_infa/libs/af_lib/operators/get_resources_db_operator.py
ceh_core_infa/libs/af_lib/operators/get_resources_service_operator.py
ceh_core_infa/libs/af_lib/operators/locked_resources_operator.py
ceh_core_infa/libs/af_lib/operators/operators.py
ceh_core_infa/libs/af_lib/operators/rollback_transaction_operator.py
ceh_core_infa/libs/af_lib/operators/update_resource_state_operator.py
ceh_core_infa/libs/af_lib/operators/interface/__init__.py
ceh_core_infa/libs/af_lib/operators/interface/base_interface.py
ceh_core_infa/libs/af_lib/operators/interface/check_block_resource_interface.py
ceh_core_infa/libs/af_lib/operators/interface/check_resource_locking_interface.py
ceh_core_infa/libs/af_lib/operators/interface/check_version_resource_interface.py
ceh_core_infa/libs/af_lib/operators/interface/commit_transaction_interface.py
ceh_core_infa/libs/af_lib/operators/interface/create_tx_interface.py
ceh_core_infa/libs/af_lib/operators/interface/get_resources_db_interface.py
