Metadata-Version: 1.0
Name: ceh-core-infa
Version: 0.3
Summary: Фреймворк для загрузки данных слоев IDL, BDM
Home-page: UNKNOWN
Author: UNKNOWN
Author-email: dimapyrin@gmail.com
License: UNKNOWN
Platform: UNKNOWN
